hicues/__init__.py
hicues/__main__.py
hicues/cue_finder.py
hicues-0.1.0.dist-info/LICENSE
hicues-0.1.0.dist-info/METADATA
hicues-0.1.0.dist-info/WHEEL
hicues-0.1.0.dist-info/entry_points.txt
hicues-0.1.0.dist-info/top_level.txt
hicues-0.1.0.dist-info/RECORD
