Metadata-Version: 2.1
Name: hicues
Version: 0.1.0
Summary: Extract cue point locations from Hindenburg Journalist projects
Home-page: https://github.com/andrashann/hicues
Author: András Hann
Author-email: dev@hann.io
License: Apache License 2.0
Platform: UNKNOWN
Classifier: Development Status :: 4 - Beta
Classifier: Programming Language :: Python :: 3
Classifier: Environment :: Console
Classifier: License :: OSI Approved :: Apache Software License
Classifier: Topic :: Multimedia :: Sound/Audio :: Editors
Classifier: Topic :: Utilities
Requires-Dist: xmltodict
Requires-Dist: watchdog
